wch341/__init__.py
wch341/driver/CH341PT.DLL
wch341/driver/CH341S64.SYS
wch341/driver/CH341S98.SYS
wch341/driver/CH341SER.CAT
wch341/driver/CH341SER.INF
wch341/driver/CH341SER.SYS
wch341/driver/CH341SER.VXD
wch341/driver/ch34x_install.exe
wch341/driver/ch34x_install.pkg
wch341/driver/DRVSETUP64/DRVSETUP64.exe
wch341-0.1.8.dist-info/METADATA
wch341-0.1.8.dist-info/WHEEL
wch341-0.1.8.dist-info/top_level.txt
wch341-0.1.8.dist-info/RECORD
